argus_ticket_gitlab.py
argus_ticket_gitlab-1.1.1.dist-info/WHEEL
argus_ticket_gitlab-1.1.1.dist-info/METADATA
argus_ticket_gitlab-1.1.1.dist-info/RECORD
