Metadata-Version: 2.1
Name: argus_ticket_gitlab
Version: 1.1.1
Summary: Allow argus-server to create tickets in Gitlab
Author-email: Johanna England <johanna.england@sikt.no>
Maintainer-email: Johanna England <johanna.england@sikt.no>
Requires-Python: >=3.8
Classifier: Framework :: Django
Classifier: Framework :: Django :: 4.2
Classifier: Intended Audience :: Information Technology
Classifier: Intended Audience :: System Administrators
Classifier: License :: OSI Approved :: GNU General Public License v3 or later (GPLv3+)
Classifier: Programming Language :: Python :: 3 :: Only
Classifier: Programming Language :: Python :: 3.8
Classifier: Programming Language :: Python :: 3.9
Classifier: Programming Language :: Python :: 3.10
Classifier: Programming Language :: Python :: 3.11
Classifier: Topic :: System :: Monitoring
Requires-Dist: argus-server>=1.15
Requires-Dist: markdownify>=0.11
Requires-Dist: python-gitlab>=3.12
Requires-Dist: tox ; extra == "test"
Requires-Dist: coverage ; extra == "test"
Project-URL: Home, https://github.com/Uninett/argus_ticket_gitlab
Project-URL: Issues, https://github.com/Uninett/argus_ticket_gitlab/issues
Provides-Extra: test
